plugin_supports/__init__.py
plugin_supports/context.py
plugin_supports/db.py
plugin_supports/plugin_interface.py
plugin_supports/plugins_support.py
pluginframeworksupports/__init__.py
pluginframeworksupports/context.py
pluginframeworksupports/db.py
pluginframeworksupports/plugin_interface.py
pluginframeworksupports/plugins_support.py
plugin_supports-0.2.dist-info/LICENSE
plugin_supports-0.2.dist-info/METADATA
plugin_supports-0.2.dist-info/WHEEL
plugin_supports-0.2.dist-info/top_level.txt
plugin_supports-0.2.dist-info/RECORD
