Metadata-Version: 2.1
Name: plugin-supports
Version: 0.2
License-File: LICENSE
Requires-Dist: sqlalchemy (==2.0.19)
Requires-Dist: fastapi (==0.96.0)
Requires-Dist: starlette (==0.27.0)
Requires-Dist: pydantic (==1.10.12)
